README.rst
setup.py
ziphmm/__init__.py
ziphmm/cython_funcs.c
ziphmm/wrappers.py
ziphmm.egg-info/PKG-INFO
ziphmm.egg-info/SOURCES.txt
ziphmm.egg-info/dependency_links.txt
ziphmm.egg-info/top_level.txt