Metadata-Version: 1.1
Name: ziphmm
Version: 0.0.9.9010
Summary: An implementation of the ziphmm algorithm
Home-page: https://github.com/birc-aeh/mini-ziphmm
Author: Anders Egerup Halager
Author-email: aeh@birc.au.dk
License: MIT
Keywords: hmm zip ziphmm
Platform: UNKNOWN
Classifier: Development Status :: 4 - Beta
Classifier: Environment :: Console
Classifier: Topic :: Software Development :: Libraries
Classifier: Topic :: Scientific/Engineering
Classifier: Topic :: Scientific/Engineering :: Bio-Informatics
Classifier: Intended Audience :: Science/Research
Classifier: Intended Audience :: Developers
Classifier: License :: OSI Approved :: MIT License
Classifier: Programming Language :: Python
Classifier: Programming Language :: Python :: 2
Classifier: Programming Language :: Python :: 3
